kinto_facebook/__init__.py
kinto_facebook/authentication.py
kinto_facebook/utils.py
kinto_facebook/views.py
kinto_facebook-0.1.0.dist-info/DESCRIPTION.rst
kinto_facebook-0.1.0.dist-info/METADATA
kinto_facebook-0.1.0.dist-info/RECORD
kinto_facebook-0.1.0.dist-info/WHEEL
kinto_facebook-0.1.0.dist-info/metadata.json
kinto_facebook-0.1.0.dist-info/top_level.txt
tests/__init__.py
tests/test_authentication.py
tests/test_includeme.py
tests/test_views.py
