Metadata-Version: 2.0
Name: kinto-facebook
Version: 0.1.0
Summary: Facebook Auth support in Kinto
Home-page: https://github.com/Kinto/kinto-facebook
Author: Rémy Hubscher
Author-email: hubscher.remy@gmail.com
License: Apache License (2.0)
Keywords: web services
Platform: UNKNOWN
Classifier: Programming Language :: Python
Classifier: Programming Language :: Python :: 3
Classifier: Programming Language :: Python :: 3.6
Classifier: Topic :: Internet :: WWW/HTTP
Classifier: Topic :: Internet :: WWW/HTTP :: WSGI :: Application
Classifier: License :: OSI Approved :: Apache Software License
Requires-Dist: kinto
